<stg><name>dummy_fe</name>


<trans_list>

<trans id="19" from="1" to="2">
<condition id="-1">
<or_exp><and_exp></and_exp></or_exp>
</condition>
</trans>

<trans id="20" from="2" to="3">
<condition id="-1">
<or_exp><and_exp><literal name="icmp_ln140" val="0"/>
</and_exp></or_exp>
</condition>
</trans>

<trans id="22" from="3" to="2">
<condition id="-1">
<or_exp><and_exp></and_exp></or_exp>
</condition>
</trans>
</trans_list>



<state_list>

<state id="1" st_id="1">

<operation id="4" st_id="1" stage="1" lat="1">
<core>NULL</core>
<MemPortIdVec></MemPortIdVec>
<condition id="-1">
<or_exp><and_exp></and_exp></or_exp>
</condition>

<Node id="4" bw="0" op_0_bw="0" op_1_bw="16" op_2_bw="0" op_3_bw="32" op_4_bw="32" op_5_bw="0" op_6_bw="32" op_7_bw="32" op_8_bw="0" op_9_bw="0" op_10_bw="0" op_11_bw="32" op_12_bw="32" op_13_bw="32" op_14_bw="32" op_15_bw="0" op_16_bw="0">
<![CDATA[
:0  call void (...)* @_ssdm_op_SpecInterface(i16* %out_V, [8 x i8]* @ap_fifo_str, i32 0, i32 0, [1 x i8]* @p_str, i32 0, i32 0, [1 x i8]* @p_str, [1 x i8]* @p_str, [1 x i8]* @p_str, i32 2, i32 2, i32 16, i32 16, [1 x i8]* @p_str, [1 x i8]* @p_str)

]]></Node>
<StgValue><ssdm name="specinterface_ln0"/></StgValue>
</operation>

<operation id="5" st_id="1" stage="1" lat="1">
<core>NULL</core>
<MemPortIdVec></MemPortIdVec>
<condition id="-1">
<or_exp><and_exp></and_exp></or_exp>
</condition>

<Node id="5" bw="0" op_0_bw="0" op_1_bw="16" op_2_bw="0" op_3_bw="32" op_4_bw="32" op_5_bw="0" op_6_bw="32" op_7_bw="32" op_8_bw="0" op_9_bw="0" op_10_bw="0" op_11_bw="32" op_12_bw="32" op_13_bw="32" op_14_bw="32" op_15_bw="0" op_16_bw="0">
<![CDATA[
:1  call void (...)* @_ssdm_op_SpecInterface(i16* %din_q_V, [8 x i8]* @p_str1, i32 0, i32 0, [1 x i8]* @p_str, i32 0, i32 0, [1 x i8]* @p_str, [1 x i8]* @p_str, [1 x i8]* @p_str, i32 0, i32 0, i32 0, i32 0, [1 x i8]* @p_str, [1 x i8]* @p_str)

]]></Node>
<StgValue><ssdm name="specinterface_ln0"/></StgValue>
</operation>

<operation id="6" st_id="1" stage="1" lat="1">
<core>NULL</core>
<MemPortIdVec></MemPortIdVec>
<condition id="-1">
<or_exp><and_exp></and_exp></or_exp>
</condition>

<Node id="6" bw="0" op_0_bw="0" op_1_bw="16" op_2_bw="0" op_3_bw="32" op_4_bw="32" op_5_bw="0" op_6_bw="32" op_7_bw="32" op_8_bw="0" op_9_bw="0" op_10_bw="0" op_11_bw="32" op_12_bw="32" op_13_bw="32" op_14_bw="32" op_15_bw="0" op_16_bw="0">
<![CDATA[
:2  call void (...)* @_ssdm_op_SpecInterface(i16* %din_i_V, [8 x i8]* @p_str1, i32 0, i32 0, [1 x i8]* @p_str, i32 0, i32 0, [1 x i8]* @p_str, [1 x i8]* @p_str, [1 x i8]* @p_str, i32 0, i32 0, i32 0, i32 0, [1 x i8]* @p_str, [1 x i8]* @p_str)

]]></Node>
<StgValue><ssdm name="specinterface_ln0"/></StgValue>
</operation>

<operation id="7" st_id="1" stage="1" lat="1">
<core>NULL</core>
<MemPortIdVec></MemPortIdVec>
<condition id="-1">
<or_exp><and_exp></and_exp></or_exp>
</condition>

<Node id="7" bw="0" op_0_bw="0">
<![CDATA[
:3  br label %1

]]></Node>
<StgValue><ssdm name="br_ln140"/></StgValue>
</operation>
</state>

<state id="2" st_id="2">

<operation id="8" st_id="2" stage="1" lat="1">
<core>NULL</core>
<MemPortIdVec></MemPortIdVec>
<condition id="-1">
<or_exp><and_exp></and_exp></or_exp>
</condition>

<Node id="9" bw="12" op_0_bw="12" op_1_bw="0" op_2_bw="12" op_3_bw="0">
<![CDATA[
:0  %i_0 = phi i12 [ 0, %0 ], [ %i, %2 ]

]]></Node>
<StgValue><ssdm name="i_0"/></StgValue>
</operation>

<operation id="9" st_id="2" stage="1" lat="1">
<core>Cmp</core>
<MemPortIdVec></MemPortIdVec>
<condition id="-1">
<or_exp><and_exp></and_exp></or_exp>
</condition>

<Node id="10" bw="1" op_0_bw="12" op_1_bw="12">
<![CDATA[
:1  %icmp_ln140 = icmp eq i12 %i_0, -1596

]]></Node>
<StgValue><ssdm name="icmp_ln140"/></StgValue>
</operation>

<operation id="10" st_id="2" stage="1" lat="1">
<core>NULL</core>
<MemPortIdVec></MemPortIdVec>
<condition id="-1">
<or_exp><and_exp></and_exp></or_exp>
</condition>

<Node id="11" bw="32" op_0_bw="32" op_1_bw="64" op_2_bw="64" op_3_bw="64">
<![CDATA[
:2  %empty = call i32 (...)* @_ssdm_op_SpecLoopTripCount(i64 2500, i64 2500, i64 2500)

]]></Node>
<StgValue><ssdm name="empty"/></StgValue>
</operation>

<operation id="11" st_id="2" stage="1" lat="1">
<core>AddSub</core>
<MemPortIdVec></MemPortIdVec>
<condition id="-1">
<or_exp><and_exp></and_exp></or_exp>
</condition>

<Node id="12" bw="12" op_0_bw="12" op_1_bw="12">
<![CDATA[
:3  %i = add i12 %i_0, 1

]]></Node>
<StgValue><ssdm name="i"/></StgValue>
</operation>

<operation id="12" st_id="2" stage="1" lat="1">
<core>NULL</core>
<MemPortIdVec></MemPortIdVec>
<condition id="-1">
<or_exp><and_exp></and_exp></or_exp>
</condition>

<Node id="13" bw="0" op_0_bw="1" op_1_bw="0" op_2_bw="0">
<![CDATA[
:4  br i1 %icmp_ln140, label %3, label %2

]]></Node>
<StgValue><ssdm name="br_ln140"/></StgValue>
</operation>

<operation id="13" st_id="2" stage="1" lat="1">
<core>FIFO</core>
<MemPortIdVec></MemPortIdVec>
<condition id="-1">
<or_exp><and_exp><literal name="icmp_ln140" val="0"/>
</and_exp></or_exp>
</condition>

<Node id="15" bw="16" op_0_bw="16" op_1_bw="16">
<![CDATA[
:0  %din_i_V_read = call i16 @_ssdm_op_Read.ap_fifo.volatile.i16P(i16* %din_i_V)

]]></Node>
<StgValue><ssdm name="din_i_V_read"/></StgValue>
</operation>

<operation id="14" st_id="2" stage="1" lat="1">
<core>FIFO</core>
<MemPortIdVec></MemPortIdVec>
<condition id="-1">
<or_exp><and_exp><literal name="icmp_ln140" val="0"/>
</and_exp></or_exp>
</condition>

<Node id="16" bw="0" op_0_bw="0" op_1_bw="16" op_2_bw="16">
<![CDATA[
:1  call void @_ssdm_op_Write.ap_fifo.volatile.i16P(i16* %out_V, i16 %din_i_V_read)

]]></Node>
<StgValue><ssdm name="write_ln142"/></StgValue>
</operation>

<operation id="15" st_id="2" stage="1" lat="1">
<core>FIFO</core>
<MemPortIdVec></MemPortIdVec>
<condition id="-1">
<or_exp><and_exp><literal name="icmp_ln140" val="0"/>
</and_exp></or_exp>
</condition>

<Node id="17" bw="16" op_0_bw="16" op_1_bw="16">
<![CDATA[
:2  %din_q_V_read = call i16 @_ssdm_op_Read.ap_fifo.volatile.i16P(i16* %din_q_V)

]]></Node>
<StgValue><ssdm name="din_q_V_read"/></StgValue>
</operation>

<operation id="16" st_id="2" stage="1" lat="1">
<core>NULL</core>
<MemPortIdVec></MemPortIdVec>
<condition id="-1">
<or_exp><and_exp><literal name="icmp_ln140" val="1"/>
</and_exp></or_exp>
</condition>

<Node id="21" bw="0">
<![CDATA[
:0  ret void

]]></Node>
<StgValue><ssdm name="ret_ln145"/></StgValue>
</operation>
</state>

<state id="3" st_id="3">

<operation id="17" st_id="3" stage="1" lat="1">
<core>FIFO</core>
<MemPortIdVec></MemPortIdVec>
<condition id="-1">
<or_exp><and_exp></and_exp></or_exp>
</condition>

<Node id="18" bw="0" op_0_bw="0" op_1_bw="16" op_2_bw="16" op_3_bw="0">
<![CDATA[
:3  call void @_ssdm_op_Write.ap_fifo.volatile.i16P(i16* %out_V, i16 %din_q_V_read)

]]></Node>
<StgValue><ssdm name="write_ln143"/></StgValue>
</operation>

<operation id="18" st_id="3" stage="1" lat="1">
<core>NULL</core>
<MemPortIdVec></MemPortIdVec>
<condition id="-1">
<or_exp><and_exp></and_exp></or_exp>
</condition>

<Node id="19" bw="0" op_0_bw="0">
<![CDATA[
:4  br label %1

]]></Node>
<StgValue><ssdm name="br_ln140"/></StgValue>
</operation>
</state>
</state_list>


<ports>
</ports>


<dataflows>
</dataflows>


</stg>
